pyposeidon_viz/__init__.py
pyposeidon_viz/hplot.py
pyposeidon_viz/mplot.py
pyposeidon_viz/pplot.py
pyposeidon_viz/utils.py
pyposeidon_viz-0.0.1.dist-info/LICENSE
pyposeidon_viz-0.0.1.dist-info/METADATA
pyposeidon_viz-0.0.1.dist-info/WHEEL
pyposeidon_viz-0.0.1.dist-info/RECORD
