Metadata-Version: 2.1
Name: pyposeidon-viz
Version: 0.0.1
Summary: 
Author: Panos Mavrogiorgos
Author-email: pmav99@gmail.com
Requires-Python: >=3.9
Classifier: Programming Language :: Python :: 3
Classifier: Programming Language :: Python :: 3.9
Classifier: Programming Language :: Python :: 3.10
Classifier: Programming Language :: Python :: 3.11
Classifier: Programming Language :: Python :: 3.12
Requires-Dist: cartopy
Requires-Dist: datashader
Requires-Dist: geopandas
Requires-Dist: geoviews
Requires-Dist: holoviews
Requires-Dist: hvplot
Requires-Dist: itkwidgets
Requires-Dist: matplotlib
Requires-Dist: mayavi
Requires-Dist: numpy
Requires-Dist: pandas
Requires-Dist: shapely
Requires-Dist: spatialpandas
Requires-Dist: xarray
